bambu_connect/BambuClient.py
bambu_connect/CameraClient.py
bambu_connect/ExecuteClient.py
bambu_connect/FileClient.py
bambu_connect/WatchClient.py
bambu_connect/__init__.py
bambu_connect/utils/__init__.py
bambu_connect/utils/models.py
bambu_connect-0.3.0.dist-info/LICENSE
bambu_connect-0.3.0.dist-info/METADATA
bambu_connect-0.3.0.dist-info/WHEEL
bambu_connect-0.3.0.dist-info/top_level.txt
bambu_connect-0.3.0.dist-info/RECORD
