Metadata-Version: 2.1
Name: bambu-connect
Version: 0.3.0
Summary: Connect with your bambu printer to send and receive mqtt messages and view the Camera
Author-email: Matt Carroll <mwcarroll12@gmail.com>
Project-URL: Homepage, https://github.com/mattcar15/bambu-connect
Classifier: Programming Language :: Python :: 3
Classifier: License :: OSI Approved :: MIT License
Classifier: Operating System :: OS Independent
License-File: LICENSE
Requires-Dist: paho-mqtt
